hammerhead/__init__.py
hammerhead/_base_client.py
hammerhead/_client.py
hammerhead/_compat.py
hammerhead/_constants.py
hammerhead/_exceptions.py
hammerhead/_files.py
hammerhead/_models.py
hammerhead/_qs.py
hammerhead/_resource.py
hammerhead/_response.py
hammerhead/_streaming.py
hammerhead/_types.py
hammerhead/_version.py
hammerhead/py.typed
hammerhead/_utils/__init__.py
hammerhead/_utils/_compat.py
hammerhead/_utils/_datetime_parse.py
hammerhead/_utils/_logs.py
hammerhead/_utils/_proxy.py
hammerhead/_utils/_reflection.py
hammerhead/_utils/_resources_proxy.py
hammerhead/_utils/_streams.py
hammerhead/_utils/_sync.py
hammerhead/_utils/_transform.py
hammerhead/_utils/_typing.py
hammerhead/_utils/_utils.py
hammerhead/lib/.keep
hammerhead/resources/__init__.py
hammerhead/resources/activities.py
hammerhead/resources/oauth.py
hammerhead/resources/routes/__init__.py
hammerhead/resources/routes/file.py
hammerhead/resources/routes/routes.py
hammerhead/resources/workouts/__init__.py
hammerhead/resources/workouts/file.py
hammerhead/resources/workouts/workouts.py
hammerhead/types/__init__.py
hammerhead/types/activity_list_params.py
hammerhead/types/activity_list_response.py
hammerhead/types/activity_retrieve_response.py
hammerhead/types/activity_summary.py
hammerhead/types/oauth_authorize_params.py
hammerhead/types/oauth_deauthorize_params.py
hammerhead/types/oauth_exchange_token_params.py
hammerhead/types/oauth_exchange_token_response.py
hammerhead/types/pagination.py
hammerhead/types/route_list_params.py
hammerhead/types/route_list_response.py
hammerhead/types/route_summary.py
hammerhead/types/routes/__init__.py
hammerhead/types/routes/file_create_params.py
hammerhead/types/routes/file_update_params.py
hammerhead/types/routes/route.py
hammerhead/types/workouts/__init__.py
hammerhead/types/workouts/file_create_params.py
hammerhead/types/workouts/file_update_params.py
hammerhead/types/workouts/workout.py
hammerhead-0.1.0.dist-info/METADATA
hammerhead-0.1.0.dist-info/WHEEL
hammerhead-0.1.0.dist-info/licenses/LICENSE
hammerhead-0.1.0.dist-info/RECORD
